fbpic/__init__.py
fbpic/main.py
fbpic/boundaries/__init__.py
fbpic/boundaries/boundary_communicator.py
fbpic/boundaries/cuda_methods.py
fbpic/boundaries/field_buffer_handling.py
fbpic/boundaries/moving_window.py
fbpic/boundaries/particle_buffer_handling.py
fbpic/boundaries/pml_damping.py
fbpic/fields/__init__.py
fbpic/fields/cuda_methods.py
fbpic/fields/fields.py
fbpic/fields/interpolation_grid.py
fbpic/fields/numba_methods.py
fbpic/fields/psatd_coefs.py
fbpic/fields/smoothing.py
fbpic/fields/spectral_grid.py
fbpic/fields/utility_methods.py
fbpic/fields/spectral_transform/__init__.py
fbpic/fields/spectral_transform/cuda_methods.py
fbpic/fields/spectral_transform/fourier.py
fbpic/fields/spectral_transform/hankel.py
fbpic/fields/spectral_transform/mkl_fft.py
fbpic/fields/spectral_transform/numba_methods.py
fbpic/fields/spectral_transform/spectral_transformer.py
fbpic/lpa_utils/__init__.py
fbpic/lpa_utils/boosted_frame.py
fbpic/lpa_utils/bunch.py
fbpic/lpa_utils/external_fields.py
fbpic/lpa_utils/mirrors.py
fbpic/lpa_utils/laser/__init__.py
fbpic/lpa_utils/laser/antenna_injection.py
fbpic/lpa_utils/laser/direct_injection.py
fbpic/lpa_utils/laser/laser.py
fbpic/lpa_utils/laser/laser_profiles.py
fbpic/lpa_utils/laser/longitudinal_laser_profiles.py
fbpic/lpa_utils/laser/transverse_laser_profiles.py
fbpic/openpmd_diag/__init__.py
fbpic/openpmd_diag/boosted_field_diag.py
fbpic/openpmd_diag/boosted_particle_diag.py
fbpic/openpmd_diag/checkpoint_restart.py
fbpic/openpmd_diag/cuda_methods.py
fbpic/openpmd_diag/data_dict.py
fbpic/openpmd_diag/field_diag.py
fbpic/openpmd_diag/generic_diag.py
fbpic/openpmd_diag/inputscript_diag.py
fbpic/openpmd_diag/particle_density_diag.py
fbpic/openpmd_diag/particle_diag.py
fbpic/openpmd_diag/synchrotron_radiation_diag.py
fbpic/particles/__init__.py
fbpic/particles/particles.py
fbpic/particles/deposition/__init__.py
fbpic/particles/deposition/cuda_methods.py
fbpic/particles/deposition/cuda_methods_one_mode.py
fbpic-0.27.0.dist-info/licenses/LICENSE.txt
fbpic-0.27.0.dist-info/METADATA
fbpic-0.27.0.dist-info/WHEEL
fbpic-0.27.0.dist-info/top_level.txt
fbpic-0.27.0.dist-info/RECORD
