Metadata-Version: 2.4
Name: fbpic
Version: 0.27.0
Summary: Spectral, quasi-3D Particle-In-Cell for CPU and GPU
Home-page: http://github.com/fbpic/fbpic
Maintainer: Remi Lehe
Maintainer-email: remi.lehe@normalesup.org
License: BSD-3-Clause-LBNL
Platform: any
Classifier: Programming Language :: Python
Classifier: Development Status :: 3 - Alpha
Classifier: Natural Language :: English
Classifier: Environment :: Console
Classifier: Intended Audience :: Science/Research
Classifier: Operating System :: OS Independent
Classifier: Topic :: Scientific/Engineering :: Physics
Classifier: Programming Language :: Python :: 2.7
Classifier: Programming Language :: Python :: 3.4
Classifier: Programming Language :: Python :: 3.5
License-File: LICENSE.txt
Requires-Dist: numpy
Requires-Dist: scipy
Requires-Dist: numba
Requires-Dist: h5py
Requires-Dist: python-dateutil
Provides-Extra: picmi
Requires-Dist: picmistandard; extra == "picmi"
Requires-Dist: numexpr; extra == "picmi"
Requires-Dist: periodictable; extra == "picmi"
Dynamic: classifier
Dynamic: description
Dynamic: description-content-type
Dynamic: home-page
Dynamic: license
Dynamic: license-file
Dynamic: maintainer
Dynamic: maintainer-email
Dynamic: platform
Dynamic: provides-extra
Dynamic: requires-dist
Dynamic: summary
